{
  "@context": "https://schema.org/",
  "@type": "JobPosting",
  "url": "https://codeforsociety.org/jobs/fair-station-project-senior-platform-web-application-engineer",
  "title": "FAIR Station Project, Senior Platform & Web Application Engineer",
  "hiringOrganization": {
    "@type": "Organization",
    "name": "Code for Science & Society"
  },
  "datePosted": "2026-05-07",
  "occupationalCategory": ["open science", "open software"],
  "resume": "Senior engineer to modernize and expand RAMS into a modular, API-forward, containerized open-source platform for the global field station research community.",
  "description": "The Senior Platform & Web Application Engineer will play a key role in advancing the technical evolution of RAMS as part of the FAIR Station initiative. Working in close partnership with the Technical Lead, Product Manager, and UCNRS collaborators, this role will focus on expanding RAMS into a modular, API-forward, containerized platform designed for interoperability and reuse.\n\nThis position emphasizes thoughtful modernization of an existing production Rails application, careful expansion of API capabilities, and support for open infrastructure integrations, all while maintaining continuity of service for current users. The role blends strong web application development with platform thinking, open-source practices, and sustainable architecture design.\n\n**Employer:** Code for Science & Society (CS&S) (Fiscal Sponsor of FAIR Station)\n\n**Status and Type:** Non-Exempt Full-time, grant-funded (two years, potential extension)\n\n**Location:** Hybrid or Remote (U.S. - Pacific Time preferred)\n\n**Travel:** Occasional travel for workshops, site visits, and community events\n\n**Compensation:** $130,000 USD annually\n\n**Benefits:** Comprehensive benefits through CS&S; summary available for review upon request\n\n## The Mission and Vision\n\nField stations and marine laboratories (FSMLs) operate at a critical point in the research life-cycle, where logistics, data collection, and research practice converge. FAIR Station is a multi-year initiative to evolve the existing UC Nature Reserve Application Management System (RAMS) into an open-source, interoperable platform to support research activity across its full life-cycle. While maintaining and improving RAMS' existing functionality within UC Nature, FAIR Station aims to expand the platform to support open research workflows, integration with persistent identifier systems and research repositories, and broader adoption across the global field station community.\n\nThe project is led by the UC Curation Center (UC3) at California Digital Library (CDL) and UC Nature in close collaboration with community partners. To provide flexibility and administrative support, FAIR Station is fiscally sponsored and administratively hosted by Code for Science & Society (CS&S), a nonprofit supporting open, community-driven digital infrastructure. Funding for this position is made possible by the Gordon & Betty Moore Foundation.\n\n## Position Overview\n\nThe Senior Platform & Web Application Engineer will play a key role in advancing the technical evolution of RAMS as part of the FAIR Station initiative. Working in close partnership with the Technical Lead, Product Manager, and UCNRS collaborators, this role will focus on expanding RAMS into a modular, API-forward, containerized platform designed for interoperability and reuse.\n\nThis position emphasizes thoughtful modernization of an existing production Rails application, careful expansion of API capabilities, and support for open infrastructure integrations, all while maintaining continuity of service for current users. The role blends strong web application development with platform thinking, open-source practices, and sustainable architecture design.\n\n## Responsibilities\n\nThe Senior Platform & Web Application Engineer contributes to the technical evolution of the FAIR Station platform, working in close partnership with a technical lead, Product Manager, and UC Nature domain experts. Technical direction and architectural priorities are guided by UC3's platform stewardship and project governance, while day-to-day implementation, integration work, and iterative delivery are carried out collaboratively within the engineering team.\n\n### API & Open Infrastructure Integration\n\n- Design and implement RESTful APIs to support integrations with external research infrastructure systems (e.g., persistent identifier providers, repositories, research workflow tools)\n- Establish clear versioning, authentication, and documentation practices for public-facing APIs\n- Ensure integration patterns are maintainable, well-documented, and aligned with open infrastructure best practices\n\n### Containerization & Deployment\n\n- Support and implement transition to containerized (Docker-based) deployment environments\n- Improve CI/CD workflows, observability, and operational reliability\n- Contribute to deployment models that support both hosted and self-managed implementations\n\n### Collaboration & Delivery\n\n- Partner closely with the Product Manager on roadmap sequencing and iterative delivery\n- Collaborate with the Technical Lead and UCNRS domain experts to ensure technical decisions align with user workflows and long-term sustainability\n- Address feature requests, usability improvements, and bug fixes in coordination with stakeholders\n- Contribute to documentation and implementation guidance for future adopters\n\n### Open Source & Sustainability\n\n- Contribute to maintaining RAMS as a public, open-source platform\n- Support documentation and development practices that encourage sustainability and reuse\n- Help ensure the platform remains lightweight, maintainable, and aligned with public-interest infrastructure principles\n\n### Platform & Application Evolution\n\n- Contribute to the ongoing architectural evolution of the RAMS application toward modular, reusable design patterns\n- Implement enhancements that support configurability and adoption beyond the UC system\n- Maintain system stability while incrementally modernizing components\n- Participate in architectural decision-making and documentation\n\n## Qualifications & Skills\n\n### Required\n\n- Experience building and maintaining production web applications (e.g., Ruby on Rails or similar MVC frameworks)\n- Strong backend and API design experience (RESTful services, versioning strategies, authentication/authorization patterns)\n- Experience evolving and modernizing mature applications without disrupting existing users\n- Experience containerizing applications (Docker) and deploying to cloud environments (e.g., AWS or comparable platforms)\n- Experience contributing to or working within open-source software environments\n- Strong documentation and communication skills; ability to collaborate effectively in a cross-functional, distributed team\n\n### Preferred\n\n- Experience working in Ruby on Rails applications\n- Experience designing software intended for reuse across institutions or organizations\n- Experience integrating with external APIs or ecosystem platforms\n- Familiarity with research infrastructure, scholarly communication systems, or open science ecosystems\n- Passion for building awesome open source tools for the research community\n- Experience working in grant-funded or public-interest technology environments\n\n## How to apply\n\nTo apply, please submit a letter of interest and resume detailing how your experience and qualifications align with the responsibilities of this role. Applications will be accepted on a rolling basis and closes May 20, 2026. Only candidates selected for an interview will be contacted."
}
